fashion_clip/__init__.py
fashion_clip/attention_map.py
fashion_clip/fashion_clip.py
fashion_clip/s3_client.py
fashion_clip/utils.py
fashion_clip-0.2.2.dist-info/LICENSE
fashion_clip-0.2.2.dist-info/METADATA
fashion_clip-0.2.2.dist-info/WHEEL
fashion_clip-0.2.2.dist-info/top_level.txt
fashion_clip-0.2.2.dist-info/RECORD
