Metadata-Version: 2.1
Name: fashion-clip
Version: 0.2.2
Author: Jacopo Tagliabue, Patrick John Chia, Federico Bianchi
Author-email: jtagliabue@coveo.com, pchia@coveo.com, f.bianchi@unibocconi.it
License: MIT license
Classifier: Development Status :: 2 - Pre-Alpha
Classifier: Intended Audience :: Developers
Classifier: License :: OSI Approved :: MIT License
Classifier: Natural Language :: English
Classifier: Programming Language :: Python :: 3.5
Classifier: Programming Language :: Python :: 3.6
Classifier: Programming Language :: Python :: 3.7
Classifier: Programming Language :: Python :: 3.8
Requires-Python: >=3.5
License-File: LICENSE
Requires-Dist: torch (>=1.11.0)
Requires-Dist: boto3 (>=1.10.50)
Requires-Dist: appdirs (>=1.4.4)
Requires-Dist: pandas (>=1.3.5)
Requires-Dist: pyarrow (>=7.0.0)
Requires-Dist: matplotlib (>=3.5.1)
Requires-Dist: python-dotenv (>=0.19.2)
Requires-Dist: annoy (>=1.17.0)
Requires-Dist: transformers (>=4.26.1)
Requires-Dist: ipyplot (>=1.1.1)
Requires-Dist: datasets (>=2.10.0)
Requires-Dist: validators
